<?xml version="1.0" encoding="utf-8"?>
<LanguageData>
  <Bite.label>ნაკბენი</Bite.label>
  <Blunt.label>ბლაგვი</Blunt.label>
  <Cut.label>გაჭრა</Cut.label>
  <Demolish.label>დანგრევა</Demolish.label>
  <KickMaterialInEyes.label>დარტყმის მასალა თვალებში</KickMaterialInEyes.label>
  <Poke.label>აკოცა</Poke.label>
  <Scratch.label>ნაკაწრი</Scratch.label>
  <ScratchToxic.label>ტოქსიკური ნაკაწრი</ScratchToxic.label>
  <Stab.label>დარტყმა</Stab.label>
  <ToxicBite.label>ტოქსიკური ნაკბენი</ToxicBite.label>
</LanguageData>
