<?xml version="1.0" encoding="utf-8"?>
<LanguageData>
  <WarpedObelisk_Abductor.label>დახრილი ობელისკი</WarpedObelisk_Abductor.label>
  <WarpedObelisk_Duplicator.label>დაზიანებული ობელისკი</WarpedObelisk_Duplicator.label>
  <WarpedObelisk_Labyrinth.description>დიდი მეტალის სვეტი, რომელიც გამოყოფს ფსიქიკურ ენერგიას. მისი გააქტიურება შესაძლებელია სახლში დასაბრუნებლად.</WarpedObelisk_Labyrinth.description>
  <WarpedObelisk_Labyrinth.label>დახრილი ობელისკი</WarpedObelisk_Labyrinth.label>
  <WarpedObelisk_Mutator.label>გრეხილი ობელისკი</WarpedObelisk_Mutator.label>
</LanguageData>
