<?xml version="1.0" encoding="utf-8"?>
<LanguageData>
  <ArcheanSeed.description>The seed of an archean tree. It can be planted to grow an archean tree, which converts nearby terrain into rich soil.\n\nArchean trees were bioengineered to terraform deadworlds and early-stage rimworlds. They are hardy enough to survive in the vacuum of space and produce a small amount of oxygen. The tree's delicate roots prevent it from being replanted.</ArcheanSeed.description>
  <ArcheanSeed.label>არქეანის თესლი</ArcheanSeed.label>
  <ChoppedStump_Archean.description>არქეის ხის მოჭრის შემდეგ დარჩენილი ღერო. ყუნწის ამოღება შესაძლებელია, მაგრამ ძალიან ცოტა გამოსაყენებელ ხეს იძლევა. გარეთ დატოვებული ღერო დროთა განმავლობაში გაუარესდება.</ChoppedStump_Archean.description>
  <ChoppedStump_Archean.label>დაჭრილი არქეის ღერო</ChoppedStump_Archean.label>
  <Plant_TreeArchean.description>A tree bioengineered to terraform deadworlds and early-stage rimworlds. The tree hosts a special microbial community in its roots which enriches nearby terrain into rich soil. The trees are hardy enough to survive in the vacuum of space and produce a small amount of oxygen.\n\nArchean trees are sterile, preventing them from becoming an invasive species after terraforming has been completed. They can only be grown from seeds produced on glitterworld planets. The tree's delicate root system prevents it from being replanted.</Plant_TreeArchean.description>
  <Plant_TreeArchean.label>არქეის ხე</Plant_TreeArchean.label>
  <SmashedStump_Archean.description>დაზიანებით განადგურებულია არქეის ხის ნარჩენები. მახინჯია. ყუნწის ამოღება შესაძლებელია, მაგრამ ძალიან ცოტა გამოსაყენებელ ხეს იძლევა. გარეთ დატოვებული ღერო დროთა განმავლობაში გაუარესდება.</SmashedStump_Archean.description>
  <SmashedStump_Archean.label>დამტვრეული არქეული ღერო</SmashedStump_Archean.label>
</LanguageData>
