<?xml version="1.0" encoding="utf-8"?>
<LanguageData>
  <Snake.corePart.parts.2.customLabel>მარცხენა ფილტვი</Snake.corePart.parts.2.customLabel>
  <Snake.corePart.parts.3.customLabel>მარჯვენა ფილტვი</Snake.corePart.parts.3.customLabel>
  <Snake.corePart.parts.4.customLabel>მარცხენა თირკმელი</Snake.corePart.parts.4.customLabel>
  <Snake.corePart.parts.5.customLabel>მარჯვენა თირკმელი</Snake.corePart.parts.5.customLabel>
  <Snake.corePart.parts.7.parts.1.customLabel>მარცხენა თვალი</Snake.corePart.parts.7.parts.1.customLabel>
  <Snake.corePart.parts.7.parts.2.customLabel>მარჯვენა თვალი</Snake.corePart.parts.7.parts.2.customLabel>
  <Snake.label>გველი</Snake.label>
</LanguageData>
