<?xml version="1.0" encoding="utf-8"?>
<LanguageData>
  <Human.corePart.parts.11.parts.0.parts.1.customLabel>მარცხენა თვალი</Human.corePart.parts.11.parts.0.parts.1.customLabel>
  <Human.corePart.parts.11.parts.0.parts.2.customLabel>მარჯვენა თვალი</Human.corePart.parts.11.parts.0.parts.2.customLabel>
  <Human.corePart.parts.11.parts.0.parts.3.customLabel>მარცხენა ყური</Human.corePart.parts.11.parts.0.parts.3.customLabel>
  <Human.corePart.parts.11.parts.0.parts.4.customLabel>მარჯვენა ყური</Human.corePart.parts.11.parts.0.parts.4.customLabel>
  <Human.corePart.parts.12.customLabel>მარცხენა მხრის</Human.corePart.parts.12.customLabel>
  <Human.corePart.parts.12.parts.0.customLabel>მარცხენა კლავიკულა</Human.corePart.parts.12.parts.0.customLabel>
  <Human.corePart.parts.12.parts.1.customLabel>მარცხენა მკლავი</Human.corePart.parts.12.parts.1.customLabel>
  <Human.corePart.parts.12.parts.1.parts.0.customLabel>მარცხენა მხრის</Human.corePart.parts.12.parts.1.parts.0.customLabel>
  <Human.corePart.parts.12.parts.1.parts.1.customLabel>მარცხენა რადიუსი</Human.corePart.parts.12.parts.1.parts.1.customLabel>
  <Human.corePart.parts.12.parts.1.parts.2.customLabel>მარცხენა ხელი</Human.corePart.parts.12.parts.1.parts.2.customLabel>
  <Human.corePart.parts.12.parts.1.parts.2.parts.0.customLabel>მარცხენა ვარდისფერი</Human.corePart.parts.12.parts.1.parts.2.parts.0.customLabel>
  <Human.corePart.parts.12.parts.1.parts.2.parts.1.customLabel>მარცხენა ბეჭედი თითი</Human.corePart.parts.12.parts.1.parts.2.parts.1.customLabel>
  <Human.corePart.parts.12.parts.1.parts.2.parts.2.customLabel>მარცხენა შუა თითი</Human.corePart.parts.12.parts.1.parts.2.parts.2.customLabel>
  <Human.corePart.parts.12.parts.1.parts.2.parts.3.customLabel>მარცხენა საჩვენებელი თითი</Human.corePart.parts.12.parts.1.parts.2.parts.3.customLabel>
  <Human.corePart.parts.12.parts.1.parts.2.parts.4.customLabel>მარცხენა ცერა</Human.corePart.parts.12.parts.1.parts.2.parts.4.customLabel>
  <Human.corePart.parts.13.customLabel>მარჯვენა მხრის</Human.corePart.parts.13.customLabel>
  <Human.corePart.parts.13.parts.0.customLabel>მარჯვენა კლავიკულა</Human.corePart.parts.13.parts.0.customLabel>
  <Human.corePart.parts.13.parts.1.customLabel>მარჯვენა მკლავი</Human.corePart.parts.13.parts.1.customLabel>
  <Human.corePart.parts.13.parts.1.parts.0.customLabel>მარჯვენა მხრის</Human.corePart.parts.13.parts.1.parts.0.customLabel>
  <Human.corePart.parts.13.parts.1.parts.1.customLabel>მარჯვენა რადიუსი</Human.corePart.parts.13.parts.1.parts.1.customLabel>
  <Human.corePart.parts.13.parts.1.parts.2.customLabel>მარჯვენა ხელი</Human.corePart.parts.13.parts.1.parts.2.customLabel>
  <Human.corePart.parts.13.parts.1.parts.2.parts.0.customLabel>მარჯვენა ვარდისფერი</Human.corePart.parts.13.parts.1.parts.2.parts.0.customLabel>
  <Human.corePart.parts.13.parts.1.parts.2.parts.1.customLabel>მარჯვენა ბეჭედი თითი</Human.corePart.parts.13.parts.1.parts.2.parts.1.customLabel>
  <Human.corePart.parts.13.parts.1.parts.2.parts.2.customLabel>მარჯვენა შუა თითი</Human.corePart.parts.13.parts.1.parts.2.parts.2.customLabel>
  <Human.corePart.parts.13.parts.1.parts.2.parts.3.customLabel>მარჯვენა საჩვენებელი თითი</Human.corePart.parts.13.parts.1.parts.2.parts.3.customLabel>
  <Human.corePart.parts.13.parts.1.parts.2.parts.4.customLabel>მარჯვენა ცერა</Human.corePart.parts.13.parts.1.parts.2.parts.4.customLabel>
  <Human.corePart.parts.15.customLabel>მარცხენა ფეხი</Human.corePart.parts.15.customLabel>
  <Human.corePart.parts.15.parts.0.customLabel>მარცხენა ბარძაყის ძვალი</Human.corePart.parts.15.parts.0.customLabel>
  <Human.corePart.parts.15.parts.1.customLabel>მარცხენა წვივის</Human.corePart.parts.15.parts.1.customLabel>
  <Human.corePart.parts.15.parts.2.customLabel>მარცხენა ფეხი</Human.corePart.parts.15.parts.2.customLabel>
  <Human.corePart.parts.15.parts.2.parts.0.customLabel>მარცხენა პატარა ფეხის თითი</Human.corePart.parts.15.parts.2.parts.0.customLabel>
  <Human.corePart.parts.15.parts.2.parts.1.customLabel>მარცხენა მეოთხე თითი</Human.corePart.parts.15.parts.2.parts.1.customLabel>
  <Human.corePart.parts.15.parts.2.parts.2.customLabel>მარცხენა შუა თითი</Human.corePart.parts.15.parts.2.parts.2.customLabel>
  <Human.corePart.parts.15.parts.2.parts.3.customLabel>მარცხენა მეორე თითი</Human.corePart.parts.15.parts.2.parts.3.customLabel>
  <Human.corePart.parts.15.parts.2.parts.4.customLabel>მარცხენა დიდი თითი</Human.corePart.parts.15.parts.2.parts.4.customLabel>
  <Human.corePart.parts.16.customLabel>მარჯვენა ფეხი</Human.corePart.parts.16.customLabel>
  <Human.corePart.parts.16.parts.0.customLabel>მარჯვენა ბარძაყის ძვალი</Human.corePart.parts.16.parts.0.customLabel>
  <Human.corePart.parts.16.parts.1.customLabel>მარჯვენა წვივის</Human.corePart.parts.16.parts.1.customLabel>
  <Human.corePart.parts.16.parts.2.customLabel>მარჯვენა ფეხი</Human.corePart.parts.16.parts.2.customLabel>
  <Human.corePart.parts.16.parts.2.parts.0.customLabel>მარჯვენა ფეხის თითი</Human.corePart.parts.16.parts.2.parts.0.customLabel>
  <Human.corePart.parts.16.parts.2.parts.1.customLabel>მარჯვენა მეოთხე თითი</Human.corePart.parts.16.parts.2.parts.1.customLabel>
  <Human.corePart.parts.16.parts.2.parts.2.customLabel>მარჯვენა შუა თითი</Human.corePart.parts.16.parts.2.parts.2.customLabel>
  <Human.corePart.parts.16.parts.2.parts.3.customLabel>მარჯვენა მეორე თითი</Human.corePart.parts.16.parts.2.parts.3.customLabel>
  <Human.corePart.parts.16.parts.2.parts.4.customLabel>მარჯვენა დიდი თითი</Human.corePart.parts.16.parts.2.parts.4.customLabel>
  <Human.corePart.parts.6.customLabel>მარცხენა ფილტვი</Human.corePart.parts.6.customLabel>
  <Human.corePart.parts.7.customLabel>მარჯვენა ფილტვი</Human.corePart.parts.7.customLabel>
  <Human.corePart.parts.8.customLabel>მარცხენა თირკმელი</Human.corePart.parts.8.customLabel>
  <Human.corePart.parts.9.customLabel>მარჯვენა თირკმელი</Human.corePart.parts.9.customLabel>
  <Human.label>ადამიანის</Human.label>
</LanguageData>
